src/package_matthis_bernet/converter.py
src/package_matthis_bernet/main.py
package_matthis_bernet-0.0.1.dist-info/METADATA
package_matthis_bernet-0.0.1.dist-info/WHEEL
package_matthis_bernet-0.0.1.dist-info/licenses/LICENSE
package_matthis_bernet-0.0.1.dist-info/RECORD
