Metadata-Version: 2.1
Name: package_matthis_bernet
Version: 0.0.1
Summary: Package du TP2 de Matthis Bernet
Project-URL: Homepage, https://github.com/MattiZZZ241/M1-2022-git-workflow
Author-email: Matthis_package_TP2 <matthis.bernet@isen.yncrea.fr>
License-File: LICENSE
Classifier: Programming Language :: Python :: 3
Requires-Python: >=3.7
